openapi_client/__init__.py
openapi_client/api_client.py
openapi_client/configuration.py
openapi_client/exceptions.py
openapi_client/model_utils.py
openapi_client/rest.py
openapi_client/api/__init__.py
openapi_client/api/auth_api.py
openapi_client/api/fileinfo_api.py
openapi_client/api/filemanager_api.py
openapi_client/api/fileupload_api.py
openapi_client/api/multimediafile_api.py
openapi_client/api/userinfo_api.py
openapi_client/model/__init__.py
openapi_client/model/oauth_token_authorization_code_response.py
openapi_client/model/oauth_token_device_code_response.py
openapi_client/model/oauth_token_device_token_response.py
openapi_client/model/oauth_token_refresh_token_response.py
openapi_client/model/quotaresponse.py
openapi_client/model/uinforesponse.py
netdisk_mcp_server-0.1.0.dist-info/METADATA
netdisk_mcp_server-0.1.0.dist-info/WHEEL
netdisk_mcp_server-0.1.0.dist-info/entry_points.txt
netdisk_mcp_server-0.1.0.dist-info/licenses/LICENSE
netdisk_mcp_server-0.1.0.dist-info/RECORD
