Metadata-Version: 2.4
Name: netdisk-mcp-server
Version: 0.1.0
Summary: 百度网盘 MCP Server - 通过 Model Context Protocol 提供百度网盘文件上传功能
Project-URL: Homepage, https://github.com/yourusername/netdisk-mcp-server-stdio
Project-URL: Repository, https://github.com/yourusername/netdisk-mcp-server-stdio
Project-URL: Issues, https://github.com/yourusername/netdisk-mcp-server-stdio/issues
Author-email: Your Name <your.email@example.com>
License: MIT
License-File: LICENSE
Keywords: baidu,mcp,model-context-protocol,netdisk,pan,百度网盘
Classifier: Development Status :: 4 - Beta
Classifier: Intended Audience :: Developers
Classifier: License :: OSI Approved :: MIT License
Classifier: Programming Language :: Python :: 3
Classifier: Programming Language :: Python :: 3.12
Classifier: Topic :: Internet :: File Transfer Protocol (FTP)
Classifier: Topic :: Software Development :: Libraries :: Python Modules
Requires-Python: >=3.12
Requires-Dist: aiohttp>=3.11.16
Requires-Dist: mcp[cli]>=1.6.0
Requires-Dist: python-dateutil>=2.9.0.post0
Requires-Dist: requests>=2.31.0
Requires-Dist: urllib3>=1.25.3
